{
    "31grid32_0.jpg370600": {
        "filename": "31grid32_0.jpg",
        "size": 370600,
        "regions": [
            {
                "shape_attributes": {
                    "name": "rect",
                    "x": 627,
                    "y": 387,
                    "width": 65,
                    "height": 356
                },
                "region_attributes": {
                    "name": "chilly",
                    "type": "chilly",
                    "image_quality": {
                        "good": true,
                        "frontal": true,
                        "good_illumination": true
                    }
                }
            },
            {
                "shape_attributes": {
                    "name": "rect",
                    "x": 424,
                    "y": 564,
                    "width": 290,
                    "height": 288
                },
                "region_attributes": {
                    "name": "chilly",
                    "type": "chilly",
                    "image_quality": {
                        "good": true,
                        "frontal": true,
                        "good_illumination": true
                    }
                }
            },
            {
                "shape_attributes": {
                    "name": "rect",
                    "x": 552,
                    "y": 8,
                    "width": 173,
                    "height": 195
                },
                "region_attributes": {
                    "name": "chilly",
                    "type": "chilly",
                    "image_quality": {
                        "good": true,
                        "frontal": true,
                        "good_illumination": true
                    }
                }
            },
            {
                "shape_attributes": {
                    "name": "rect",
                    "x": 637,
                    "y": 23,
                    "width": 150,
                    "height": 94
                },
                "region_attributes": {
                    "name": "chilly",
                    "type": "chilly",
                    "image_quality": {
                        "good": true,
                        "frontal": true,
                        "good_illumination": true
                    }
                }
            },
            {
                "shape_attributes": {
                    "name": "rect",
                    "x": 748,
                    "y": 27,
                    "width": 83,
                    "height": 299
                },
                "region_attributes": {
                    "name": "chilly",
                    "type": "chilly",
                    "image_quality": {
                        "good": true,
                        "frontal": true,
                        "good_illumination": true
                    }
                }
            },
            {
                "shape_attributes": {
                    "name": "rect",
                    "x": 825,
                    "y": 49,
                    "width": 71,
                    "height": 166
                },
                "region_attributes": {
                    "name": "chilly",
                    "type": "chilly",
                    "image_quality": {
                        "good": true,
                        "frontal": true,
                        "good_illumination": true
                    }
                }
            },
            {
                "shape_attributes": {
                    "name": "rect",
                    "x": 951,
                    "y": 63,
                    "width": 41,
                    "height": 349
                },
                "region_attributes": {
                    "name": "chilly",
                    "type": "chilly",
                    "image_quality": {
                        "good": true,
                        "frontal": true,
                        "good_illumination": true
                    }
                }
            }
        ],
        "file_attributes": {
            "caption": "",
            "public_domain": "no",
            "image_url": ""
        }
    }
}