{
    "32grid43_3.jpg213157": {
        "filename": "32grid43_3.jpg",
        "size": 213157,
        "regions": [
            {
                "shape_attributes": {
                    "name": "rect",
                    "x": 169,
                    "y": 18,
                    "width": 143,
                    "height": 256
                },
                "region_attributes": {
                    "name": "chilly",
                    "type": "chilly",
                    "image_quality": {
                        "good": true,
                        "frontal": true,
                        "good_illumination": true
                    }
                }
            }
        ],
        "file_attributes": {
            "caption": "",
            "public_domain": "no",
            "image_url": ""
        }
    }
}