{
    "35grid31_0.jpg345387": {
        "filename": "35grid31_0.jpg",
        "size": 345387,
        "regions": [
            {
                "shape_attributes": {
                    "name": "rect",
                    "x": 466,
                    "y": 333,
                    "width": 100,
                    "height": 570
                },
                "region_attributes": {
                    "name": "not_defined",
                    "type": "unknown",
                    "image_quality": {
                        "good": true,
                        "frontal": true,
                        "good_illumination": true
                    }
                }
            },
            {
                "shape_attributes": {
                    "name": "rect",
                    "x": 8,
                    "y": 744,
                    "width": 188,
                    "height": 192
                },
                "region_attributes": {
                    "name": "not_defined",
                    "type": "unknown",
                    "image_quality": {
                        "good": true,
                        "frontal": true,
                        "good_illumination": true
                    }
                }
            },
            {
                "shape_attributes": {
                    "name": "rect",
                    "x": 88,
                    "y": 736,
                    "width": 125,
                    "height": 258
                },
                "region_attributes": {
                    "name": "not_defined",
                    "type": "unknown",
                    "image_quality": {
                        "good": true,
                        "frontal": true,
                        "good_illumination": true
                    }
                }
            },
            {
                "shape_attributes": {
                    "name": "rect",
                    "x": 446,
                    "y": 16,
                    "width": 178,
                    "height": 211
                },
                "region_attributes": {
                    "name": "not_defined",
                    "type": "unknown",
                    "image_quality": {
                        "good": true,
                        "frontal": true,
                        "good_illumination": true
                    }
                }
            },
            {
                "shape_attributes": {
                    "name": "rect",
                    "x": 607,
                    "y": 20,
                    "width": 286,
                    "height": 397
                },
                "region_attributes": {
                    "name": "not_defined",
                    "type": "unknown",
                    "image_quality": {
                        "good": true,
                        "frontal": true,
                        "good_illumination": true
                    }
                }
            },
            {
                "shape_attributes": {
                    "name": "rect",
                    "x": 276,
                    "y": 55,
                    "width": 217,
                    "height": 102
                },
                "region_attributes": {
                    "name": "not_defined",
                    "type": "unknown",
                    "image_quality": {
                        "good": true,
                        "frontal": true,
                        "good_illumination": true
                    }
                }
            },
            {
                "shape_attributes": {
                    "name": "rect",
                    "x": 746,
                    "y": 311,
                    "width": 194,
                    "height": 470
                },
                "region_attributes": {
                    "name": "not_defined",
                    "type": "unknown",
                    "image_quality": {
                        "good": true,
                        "frontal": true,
                        "good_illumination": true
                    }
                }
            }
        ],
        "file_attributes": {
            "caption": "",
            "public_domain": "no",
            "image_url": ""
        }
    }
}