{
    "36grid43_1.jpg208114": {
        "filename": "36grid43_1.jpg",
        "size": 208114,
        "regions": [
            {
                "shape_attributes": {
                    "name": "rect",
                    "x": 541,
                    "y": 140,
                    "width": 110,
                    "height": 397
                },
                "region_attributes": {
                    "name": "chilly",
                    "type": "chilly",
                    "image_quality": {
                        "good": true,
                        "frontal": true,
                        "good_illumination": true
                    }
                }
            },
            {
                "shape_attributes": {
                    "name": "rect",
                    "x": 646,
                    "y": 100,
                    "width": 86,
                    "height": 302
                },
                "region_attributes": {
                    "name": "chilly",
                    "type": "chilly",
                    "image_quality": {
                        "good": true,
                        "frontal": true,
                        "good_illumination": true
                    }
                }
            },
            {
                "shape_attributes": {
                    "name": "rect",
                    "x": 279,
                    "y": 290,
                    "width": 66,
                    "height": 348
                },
                "region_attributes": {
                    "name": "chilly",
                    "type": "chilly",
                    "image_quality": {
                        "good": true,
                        "frontal": true,
                        "good_illumination": true
                    }
                }
            },
            {
                "shape_attributes": {
                    "name": "rect",
                    "x": 305,
                    "y": 288,
                    "width": 60,
                    "height": 239
                },
                "region_attributes": {
                    "name": "chilly",
                    "type": "chilly",
                    "image_quality": {
                        "good": true,
                        "frontal": true,
                        "good_illumination": true
                    }
                }
            }
        ],
        "file_attributes": {
            "caption": "",
            "public_domain": "no",
            "image_url": ""
        }
    }
}